django_email/__init__.py
django_email/email_utils.py
django_email/templates/email_interest.html
django_email/templates/email_login.html
django_email/templates/email_ticket.html
django_email/templates/email_welcome.html
django_email_package-0.0.2.dist-info/LICENSE
django_email_package-0.0.2.dist-info/METADATA
django_email_package-0.0.2.dist-info/WHEEL
django_email_package-0.0.2.dist-info/top_level.txt
django_email_package-0.0.2.dist-info/RECORD
