Metadata-Version: 2.1
Name: django_email_package
Version: 0.0.2
Summary: A Python package for sending HTML-formatted emails in Django
Author-email: Didheemose <sebastiandidheemose2002@gmail.com>
Project-URL: Homepage, https://github.com/DidheemosePS/django_email_package
Project-URL: Issues, https://github.com/DidheemosePS/django_email_package/issues
Classifier: Programming Language :: Python :: 3
Classifier: License :: OSI Approved :: MIT License
Classifier: Operating System :: OS Independent
Requires-Python: >=3.8
License-File: LICENSE
